restee/__init__.py
restee/core.py
restee/images.py
restee/tables.py
restee/values.py
restee-0.0.3.dist-info/LICENSE
restee-0.0.3.dist-info/METADATA
restee-0.0.3.dist-info/WHEEL
restee-0.0.3.dist-info/top_level.txt
restee-0.0.3.dist-info/RECORD
