Metadata-Version: 2.1
Name: restee
Version: 0.0.3
Summary: Python package to call processed EE objects via the REST API to local data
Home-page: http://github.com/kmarkert/restee
Author: Kel Markert
Author-email: kel.markert@gmail.com
License: MIT
Platform: UNKNOWN
Requires-Dist: numpy
Requires-Dist: scipy
Requires-Dist: pandas
Requires-Dist: xarray
Requires-Dist: rasterio
Requires-Dist: geopandas
Requires-Dist: pyproj
Requires-Dist: requests
Requires-Dist: backoff
Requires-Dist: earthengine-api
Requires-Dist: tqdm
